xamphp/__init__.py
xamphp/main.py
xamphp/.system/imports.py
xamphp/.system/index.py
xamphp/.system/modules/localhost.py
xamphp/.system/sources/clight.json
xamphp/.system/sources/hosts
xamphp/.system/sources/logo.ico
xamphp/.system/sources/vhosts.conf
xamphp-1.0.5.dist-info/licenses/LICENSE
xamphp-1.0.5.dist-info/METADATA
xamphp-1.0.5.dist-info/WHEEL
xamphp-1.0.5.dist-info/entry_points.txt
xamphp-1.0.5.dist-info/top_level.txt
xamphp-1.0.5.dist-info/RECORD
