Metadata-Version: 2.4
Name: xamphp
Version: 1.0.5
Summary: XAMPHP is a command-line interface app designed to launch PHP projects via XAMPP engine from any location on your Windows machine as a virtual local host
Home-page: https://github.com/IG-onGit/XAMPHP
Author: Irakli Gzirishvili
Author-email: gziraklirex@gmail.com
Classifier: Programming Language :: Python :: 3
Classifier: License :: OSI Approved :: MIT License
Classifier: Operating System :: Microsoft :: Windows
License-File: LICENSE
Requires-Dist: clight
Dynamic: author
Dynamic: author-email
Dynamic: classifier
Dynamic: description
Dynamic: description-content-type
Dynamic: home-page
Dynamic: license-file
Dynamic: requires-dist
Dynamic: summary
